currency_converter/__init__.py
currency_converter/converter.py
north_coders_currency_converter-1.1.0.dist-info/METADATA
north_coders_currency_converter-1.1.0.dist-info/WHEEL
north_coders_currency_converter-1.1.0.dist-info/top_level.txt
north_coders_currency_converter-1.1.0.dist-info/RECORD
